.pypirc
HISTORY.txt
MANIFEST.in
README.md
distribute-0.6.24.tar.gz
setup.py
pythonpackages_scaffolds/__init__.py
pythonpackages_scaffolds.egg-info/PKG-INFO
pythonpackages_scaffolds.egg-info/SOURCES.txt
pythonpackages_scaffolds.egg-info/dependency_links.txt
pythonpackages_scaffolds.egg-info/entry_points.txt
pythonpackages_scaffolds.egg-info/requires.txt
pythonpackages_scaffolds.egg-info/top_level.txt
pythonpackages_scaffolds/plone_theme/HISTORY.txt_tmpl
pythonpackages_scaffolds/plone_theme/README.txt_tmpl
pythonpackages_scaffolds/plone_theme/setup.py_tmpl
pythonpackages_scaffolds/plone_theme/+namespace_package+/__init__.py_tmpl
pythonpackages_scaffolds/plone_theme/+namespace_package+/+package+/__init__.py_tmpl
pythonpackages_scaffolds/plone_theme/+namespace_package+/+package+/configure.zcml
pythonpackages_scaffolds/plone_theme/+namespace_package+/+package+/static/index.html
pythonpackages_scaffolds/plone_theme/+namespace_package+/+package+/static/rules.xml