Metadata-Version: 1.0
Name: pythonpackages-scaffolds
Version: 0.0.1
Summary: PasteScript paster templates for pythonpackages.com
Home-page: UNKNOWN
Author: Alex Clark
Author-email: aclark@aclark.net
License: UNKNOWN
Platform: UNKNOWN
